st2aws/__init__.py
st2aws/action.py
st2aws/ec2.py
st2aws/ec2parsers.py
st2aws/parsers.py
st2aws-0.0.14.dist-info/DESCRIPTION.rst
st2aws-0.0.14.dist-info/METADATA
st2aws-0.0.14.dist-info/RECORD
st2aws-0.0.14.dist-info/WHEEL
st2aws-0.0.14.dist-info/metadata.json
st2aws-0.0.14.dist-info/top_level.txt
