Metadata-Version: 2.0
Name: st2aws
Version: 0.0.14
Summary: Stackstorm AWS shared files
Home-page: https://github.com/StackStorm-Exchange
Author: Andy Moore
Author-email: pypi@impulsed.net
License: MIT
Keywords: stackstorm aws automation
Platform: UNKNOWN
Classifier: Development Status :: 3 - Alpha
Classifier: Intended Audience :: Developers
Classifier: Topic :: Software Development :: Build Tools
Classifier: License :: OSI Approved :: MIT License
Classifier: Programming Language :: Python :: 2
Classifier: Programming Language :: Python :: 2.7
